{
    "message": "project scheme",
    "status": true,
    "data": [
    {
        "id": "64b5df793ecfb161a74c68ba",
        "index": 0,
        "balance": "3,057,068,254.63",
        "onGoingFund": "1,454,314,399.69",
        "onClosingFund": "3,792,141,462.30",
        "projectCount": 326,
        "onGoingCount": 334,
        "onClosingCount": 27,
        "registered": "2017-07-03T11:33:05 -07:00",
        "projectPerScheme": "inter. collaboration"
    },
    {
        "id": "64b5df79a73ba5b4d62215be",
        "index": 1,
        "balance": "3,943,670,634.36",
        "onGoingFund": "2,020,383,937.31",
        "onClosingFund": "2,423,332,393.18",
        "projectCount": 455,
        "onGoingCount": 430,
        "onClosingCount": 292,
        "registered": "2021-04-25T03:52:01 -07:00",
        "projectPerScheme": "invitation"
    },
    {
        "id": "64b5df79faff6131ad086bc7",
        "index": 2,
        "balance": "2,302,152,689.22",
        "onGoingFund": "3,778,257,120.29",
        "onClosingFund": "3,652,391,210.68",
        "projectCount": 308,
        "onGoingCount": 306,
        "onClosingCount": 248,
        "registered": "2017-02-26T10:58:04 -07:00",
        "projectPerScheme": "mandatory"
    },
    {
        "id": "64b5df79f781453871ba9683",
        "index": 3,
        "balance": "1,494,039,506.94",
        "onGoingFund": "1,935,030,337.66",
        "onClosingFund": "1,304,008,180.38",
        "projectCount": 176,
        "onGoingCount": 168,
        "onClosingCount": 261,
        "registered": "2018-08-07T05:03:46 -07:00",
        "projectPerScheme": "invitation"
    },
    {
        "id": "64b5df7981c613e66db8a96b",
        "index": 4,
        "balance": "1,994,358,726.76",
        "onGoingFund": "1,395,225,570.99",
        "onClosingFund": "3,549,474,242.51",
        "projectCount": 50,
        "onGoingCount": 299,
        "onClosingCount": 153,
        "registered": "2021-11-19T12:14:05 -07:00",
        "projectPerScheme": "invitation"
    },
    {
        "id": "64b5df79d0c485877d0ba2a3",
        "index": 5,
        "balance": "2,692,791,474.10",
        "onGoingFund": "3,970,288,768.13",
        "onClosingFund": "3,446,206,357.89",
        "projectCount": 692,
        "onGoingCount": 208,
        "onClosingCount": 137,
        "registered": "2015-01-15T08:27:48 -07:00",
        "projectPerScheme": "inter. collaboration"
    },
    {
        "id": "64b5df7988c45b761eb4ecf2",
        "index": 6,
        "balance": "3,456,753,270.03",
        "onGoingFund": "2,700,276,612.25",
        "onClosingFund": "3,505,993,121.92",
        "projectCount": 124,
        "onGoingCount": 58,
        "onClosingCount": 229,
        "registered": "2015-04-07T02:46:47 -07:00",
        "projectPerScheme": "invitation"
    },
    {
        "id": "64b5df79748ec58ac13ca7a2",
        "index": 7,
        "balance": "2,136,240,919.09",
        "onGoingFund": "2,022,478,132.54",
        "onClosingFund": "1,851,188,479.58",
        "projectCount": 427,
        "onGoingCount": 356,
        "onClosingCount": 70,
        "registered": "2021-06-22T03:09:03 -07:00",
        "projectPerScheme": "mandatory"
    },
    {
        "id": "64b5df799795508d5bf3f259",
        "index": 8,
        "balance": "3,151,874,958.02",
        "onGoingFund": "1,278,201,299.13",
        "onClosingFund": "1,984,788,758.79",
        "projectCount": 850,
        "onGoingCount": 464,
        "onClosingCount": 232,
        "registered": "2021-01-18T08:31:50 -07:00",
        "projectPerScheme": "invitation"
    },
    {
        "id": "64b5df79ceacfdd8560ffc6e",
        "index": 9,
        "balance": "2,823,258,784.59",
        "onGoingFund": "2,146,032,118.52",
        "onClosingFund": "1,370,466,314.85",
        "projectCount": 839,
        "onGoingCount": 211,
        "onClosingCount": 102,
        "registered": "2021-10-27T01:36:03 -07:00",
        "projectPerScheme": "competition"
    },
    {
        "id": "64b5df79a74f9d2ccf6a34fb",
        "index": 10,
        "balance": "3,111,644,849.91",
        "onGoingFund": "1,308,054,253.25",
        "onClosingFund": "1,819,637,627.62",
        "projectCount": 805,
        "onGoingCount": 508,
        "onClosingCount": 201,
        "registered": "2016-06-25T08:43:51 -07:00",
        "projectPerScheme": "invitation"
    },
    {
        "id": "64b5df79510e019b835f5384",
        "index": 11,
        "balance": "2,003,455,373.91",
        "onGoingFund": "3,314,853,969.14",
        "onClosingFund": "1,928,093,625.84",
        "projectCount": 307,
        "onGoingCount": 180,
        "onClosingCount": 196,
        "registered": "2021-10-13T04:24:53 -07:00",
        "projectPerScheme": "inter. collaboration"
    },
    {
        "id": "64b5df79ec29eaa16a2a094f",
        "index": 12,
        "balance": "3,530,922,914.09",
        "onGoingFund": "2,489,823,827.80",
        "onClosingFund": "1,993,166,918.07",
        "projectCount": 39,
        "onGoingCount": 467,
        "onClosingCount": 66,
        "registered": "2014-08-17T10:57:30 -07:00",
        "projectPerScheme": "competition"
    },
    {
        "id": "64b5df792ec8a5bcb1256a1a",
        "index": 13,
        "balance": "3,519,082,933.41",
        "onGoingFund": "2,608,193,866.34",
        "onClosingFund": "1,247,263,655.29",
        "projectCount": 93,
        "onGoingCount": 641,
        "onClosingCount": 239,
        "registered": "2020-06-04T09:32:41 -07:00",
        "projectPerScheme": "inter. collaboration"
    },
    {
        "id": "64b5df79a092042b90d4d758",
        "index": 14,
        "balance": "2,749,298,914.70",
        "onGoingFund": "1,168,660,325.17",
        "onClosingFund": "3,195,523,908.95",
        "projectCount": 866,
        "onGoingCount": 400,
        "onClosingCount": 263,
        "registered": "2020-12-20T05:17:18 -07:00",
        "projectPerScheme": "competition"
    },
    {
        "id": "64b5df79563cb922495cbc9c",
        "index": 15,
        "balance": "3,717,177,410.60",
        "onGoingFund": "1,033,387,484.63",
        "onClosingFund": "1,550,662,802.50",
        "projectCount": 168,
        "onGoingCount": 175,
        "onClosingCount": 138,
        "registered": "2017-05-28T12:46:09 -07:00",
        "projectPerScheme": "competition"
    },
    {
        "id": "64b5df7967f38c658fc3ecf8",
        "index": 16,
        "balance": "1,544,656,283.42",
        "onGoingFund": "1,452,348,310.55",
        "onClosingFund": "2,897,467,849.36",
        "projectCount": 485,
        "onGoingCount": 672,
        "onClosingCount": 105,
        "registered": "2016-07-09T07:14:18 -07:00",
        "projectPerScheme": "inter. collaboration"
    },
    {
        "id": "64b5df79a2d206ecab0af933",
        "index": 17,
        "balance": "3,967,448,351.67",
        "onGoingFund": "1,352,595,977.59",
        "onClosingFund": "2,359,557,959.04",
        "projectCount": 191,
        "onGoingCount": 84,
        "onClosingCount": 126,
        "registered": "2017-09-18T01:31:56 -07:00",
        "projectPerScheme": "invitation"
    },
    {
        "id": "64b5df7981415d7316a9f5bc",
        "index": 18,
        "balance": "3,687,982,065.74",
        "onGoingFund": "3,026,139,451.09",
        "onClosingFund": "1,171,531,657.36",
        "projectCount": 648,
        "onGoingCount": 253,
        "onClosingCount": 155,
        "registered": "2017-10-23T05:19:45 -07:00",
        "projectPerScheme": "mandatory"
    },
    {
        "id": "64b5df79f1f63562e3b6b810",
        "index": 19,
        "balance": "1,638,310,002.27",
        "onGoingFund": "2,189,236,514.80",
        "onClosingFund": "1,086,244,581.78",
        "projectCount": 270,
        "onGoingCount": 60,
        "onClosingCount": 78,
        "registered": "2015-05-23T08:51:56 -07:00",
        "projectPerScheme": "competition"
    }
]
}
